serpentscribe/__init__.py
serpentscribe/logger.py
tests/__init__.py
tests/test_serpentscribe.py
serpentscribe-0.3.dist-info/LICENSE
serpentscribe-0.3.dist-info/METADATA
serpentscribe-0.3.dist-info/WHEEL
serpentscribe-0.3.dist-info/top_level.txt
serpentscribe-0.3.dist-info/RECORD
