Metadata-Version: 2.1
Name: serpentscribe
Version: 0.3
Summary: A fast, simple, and yet powerful Python logging library designed to make function call logging effortless. No longer do you have to instantiate logging multiple times within a function or class. This module provides a simple decorator to automatically log the details of function calls, including arguments and return values to stdout and optionally to a JSON file specified.
Home-page: https://github.com/dad2jrn/serpentscribe
Author: Ron Meck
Author-email: dad2jrn@gmail.com
License: MIT
License-File: LICENSE
